{
  "paragraphs": [
    {
      "text": "%spark\nimport spark.implicits._\n\nval bookGenres \u003d spark.read.parquet(\"/odsc/books_genres.parquet.parquet\")\nbookGenres.printSchema\nbookGenres.createOrReplaceTempView(\"books_genres\")",
      "user": "anonymous",
      "dateUpdated": "2020-02-17 18:23:07.419",
      "config": {
        "editorSetting": {
          "language": "scala",
          "editOnDblClick": false,
          "completionKey": "TAB",
          "completionSupport": true
        },
        "colWidth": 12.0,
        "editorMode": "ace/mode/scala",
        "fontSize": 9.0,
        "results": {},
        "enabled": true
      },
      "settings": {
        "params": {},
        "forms": {}
      },
      "results": {
        "code": "SUCCESS",
        "msg": [
          {
            "type": "TEXT",
            "data": "root\n |-- genreBookId: long (nullable \u003d true)\n |-- genreName: string (nullable \u003d true)\n |-- userTaggedCount: long (nullable \u003d true)\n\nimport spark.implicits._\nbookGenres: org.apache.spark.sql.DataFrame \u003d [genreBookId: bigint, genreName: string ... 1 more field]\n"
          }
        ]
      },
      "apps": [],
      "jobName": "paragraph_1581963787419_1796787524",
      "id": "20191030-014613_860020814",
      "dateCreated": "2020-02-17 18:23:07.419",
      "status": "READY",
      "errorMessage": "",
      "progressUpdateIntervalMs": 500
    },
    {
      "text": "%sql\nselect\n  genreName, sum(userTaggedCount) as totalTagged,\n  count(genreBookId) as booksTagged\n  from books_genres\n  group by genreName\n  having booksTagged \u003e 1000\n  order by totalTagged desc",
      "user": "anonymous",
      "dateUpdated": "2020-02-17 18:23:07.419",
      "config": {
        "editorSetting": {
          "language": "sql",
          "editOnDblClick": false,
          "completionKey": "TAB",
          "completionSupport": true
        },
        "colWidth": 12.0,
        "editorMode": "ace/mode/sql",
        "fontSize": 9.0,
        "results": {
          "0": {
            "graph": {
              "mode": "table",
              "height": 300.0,
              "optionOpen": false,
              "setting": {
                "table": {
                  "tableGridState": {},
                  "tableColumnTypeState": {
                    "names": {
                      "genreName": "string",
                      "totalTagged": "string",
                      "booksTagged": "string"
                    },
                    "updated": false
                  },
                  "tableOptionSpecHash": "[{\"name\":\"useFilter\",\"valueType\":\"boolean\",\"defaultValue\":false,\"widget\":\"checkbox\",\"description\":\"Enable filter for columns\"},{\"name\":\"showPagination\",\"valueType\":\"boolean\",\"defaultValue\":false,\"widget\":\"checkbox\",\"description\":\"Enable pagination for better navigation\"},{\"name\":\"showAggregationFooter\",\"valueType\":\"boolean\",\"defaultValue\":false,\"widget\":\"checkbox\",\"description\":\"Enable a footer for displaying aggregated values\"}]",
                  "tableOptionValue": {
                    "useFilter": false,
                    "showPagination": false,
                    "showAggregationFooter": false
                  },
                  "updated": false,
                  "initialized": false
                }
              },
              "commonSetting": {}
            }
          }
        },
        "enabled": true
      },
      "settings": {
        "params": {},
        "forms": {}
      },
      "results": {
        "code": "SUCCESS",
        "msg": [
          {
            "type": "TABLE",
            "data": "genreName\ttotalTagged\tbooksTagged\nto-read\t250004405\t5202\ncurrently-reading\t15602994\t4898\nclassics\t5482701\t2575\nfiction\t4928918\t4032\nfavorites\t4838359\t4366\nfantasy\t2603369\t1573\nowned\t1331123\t4605\nbooks-i-own\t1158371\t4334\nclassic\t904944\t1731\nhistorical-fiction\t768679\t1610\nnon-fiction\t715991\t1843\nliterature\t548078\t2574\nyoung-adult\t532570\t1003\nfavourites\t451512\t2450\nmystery\t423101\t1083\nnovels\t404462\t2641\nromance\t398602\t1115\nowned-books\t381445\t3900\nbook-club\t320915\t1954\nhistory\t320859\t1723\ndefault\t318259\t4251\nnonfiction\t295002\t1533\nlibrary\t279577\t4117\nkindle\t275926\t3155\nschool\t271816\t1360\naudiobook\t249379\t2372\nhistorical\t237073\t1559\nseries\t235631\t1245\nto-buy\t235261\t3512\nadult\t233869\t2414\nadventure\t233652\t1176\naudiobooks\t214208\t2294\nmy-library\t213824\t3569\nphilosophy\t209116\t1022\nnovel\t206120\t2263\nmy-books\t203439\t3206\ndrama\t188016\t1315\ncontemporary\t174091\t1768\nre-read\t168468\t1642\nadult-fiction\t166773\t1857\nebook\t158445\t2983\naudio\t139143\t2040\nenglish\t138857\t1995\ni-own\t138167\t2601\nall-time-favorites\t137137\t1263\nliterary-fiction\t131535\t1471\nabandoned\t125006\t2053\ngeneral-fiction\t110625\t1660\namerican\t100875\t1472\nbooks\t100131\t2077\nfavorite-books\t99821\t1034\nebooks\t99381\t2242\nown-it\t92530\t2335\nfavorite\t87763\t1075\n20th-century\t87091\t1641\ndnf\t82197\t1292\naudible\t76177\t1350\ndid-not-finish\t75081\t1427\nwish-list\t72484\t2607\ncontemporary-fiction\t71994\t1071\nunfinished\t65212\t1427\nbookshelf\t59670\t1380\nliterary\t59460\t1233\ntbr\t56928\t1130\nhome-library\t56419\t2143\naudio-books\t43939\t1054\nhave\t40472\t1607\nto-read-fiction\t33204\t1039\ne-book\t24632\t1237\ne-books\t22978\t1142\npersonal-library\t19011\t1037\nunread\t8617\t1017\n"
          },
          {
            "type": "TEXT",
            "data": ""
          }
        ]
      },
      "apps": [],
      "jobName": "paragraph_1581963787419_-1908947347",
      "id": "20191030-020521_344635581",
      "dateCreated": "2020-02-17 18:23:07.419",
      "status": "READY",
      "errorMessage": "",
      "progressUpdateIntervalMs": 500
    },
    {
      "text": "%spark\nval booksWithPublisherRank \u003d spark.read.parquet(\"/odsc/books_publisher_predictions.parquet\")\nbooksWithPublisherRank.printSchema\nbooksWithPublisherRank.createOrReplaceTempView(\"books_publisher_predictions\")",
      "user": "anonymous",
      "dateUpdated": "2020-02-17 18:23:07.419",
      "config": {
        "editorSetting": {
          "language": "scala",
          "editOnDblClick": false,
          "completionKey": "TAB",
          "completionSupport": true
        },
        "colWidth": 12.0,
        "editorMode": "ace/mode/scala",
        "fontSize": 9.0,
        "results": {},
        "enabled": true
      },
      "settings": {
        "params": {},
        "forms": {}
      },
      "results": {
        "code": "SUCCESS",
        "msg": [
          {
            "type": "TEXT",
            "data": "root\n |-- averageRating: double (nullable \u003d true)\n |-- countryCode: string (nullable \u003d true)\n |-- description: string (nullable \u003d true)\n |-- id: long (nullable \u003d true)\n |-- isEbook: boolean (nullable \u003d true)\n |-- isbn: string (nullable \u003d true)\n |-- isbn13: string (nullable \u003d true)\n |-- languageCode: string (nullable \u003d true)\n |-- numPages: long (nullable \u003d true)\n |-- publicationDay: long (nullable \u003d true)\n |-- publicationMonth: long (nullable \u003d true)\n |-- publicationYear: long (nullable \u003d true)\n |-- publisher: string (nullable \u003d true)\n |-- ratingsCount: long (nullable \u003d true)\n |-- ratingsDist: string (nullable \u003d true)\n |-- title: string (nullable \u003d true)\n |-- prediction: integer (nullable \u003d true)\n\nbooksWithPublisherRank: org.apache.spark.sql.DataFrame \u003d [averageRating: double, countryCode: string ... 15 more fields]\n"
          }
        ]
      },
      "apps": [],
      "jobName": "paragraph_1581963787419_1830727355",
      "id": "20191030-020704_195932495",
      "dateCreated": "2020-02-17 18:23:07.419",
      "status": "READY",
      "errorMessage": "",
      "progressUpdateIntervalMs": 500
    },
    {
      "text": "%spark\nval genreToBookWithPublisherAndRankTable \u003d bookGenres.join(booksWithPublisherRank).where($\"genreBookId\" \u003d\u003d\u003d $\"id\")",
      "user": "anonymous",
      "dateUpdated": "2020-02-17 18:23:07.420",
      "config": {
        "editorSetting": {
          "language": "scala",
          "editOnDblClick": false,
          "completionKey": "TAB",
          "completionSupport": true
        },
        "colWidth": 12.0,
        "editorMode": "ace/mode/scala",
        "fontSize": 9.0,
        "results": {},
        "enabled": true
      },
      "settings": {
        "params": {},
        "forms": {}
      },
      "results": {
        "code": "SUCCESS",
        "msg": [
          {
            "type": "TEXT",
            "data": "genreToBookWithPublisherAndRankTable: org.apache.spark.sql.Dataset[org.apache.spark.sql.Row] \u003d [genreBookId: bigint, genreName: string ... 18 more fields]\n"
          }
        ]
      },
      "apps": [],
      "jobName": "paragraph_1581963787420_-348956859",
      "id": "20191030-021258_713429083",
      "dateCreated": "2020-02-17 18:23:07.420",
      "status": "READY",
      "errorMessage": "",
      "progressUpdateIntervalMs": 500
    },
    {
      "text": "%spark\ngenreToBookWithPublisherAndRankTable.createOrReplaceTempView(\"genre_book_publisher_rank\")",
      "user": "anonymous",
      "dateUpdated": "2020-02-17 18:23:07.420",
      "config": {
        "editorSetting": {
          "language": "scala",
          "editOnDblClick": false,
          "completionKey": "TAB",
          "completionSupport": true
        },
        "colWidth": 12.0,
        "editorMode": "ace/mode/scala",
        "fontSize": 9.0,
        "results": {},
        "enabled": true
      },
      "settings": {
        "params": {},
        "forms": {}
      },
      "results": {
        "code": "SUCCESS",
        "msg": []
      },
      "apps": [],
      "jobName": "paragraph_1581963787420_1604058242",
      "id": "20191030-021731_444621441",
      "dateCreated": "2020-02-17 18:23:07.420",
      "status": "READY",
      "errorMessage": "",
      "progressUpdateIntervalMs": 500
    },
    {
      "text": "%sql\nselect genreName,\n  sum(userTaggedCount) as totalTagged\n  from genre_book_publisher_rank\n  where prediction \u003d 2\n  group by genreName\n  order by totalTagged desc limit 100",
      "user": "anonymous",
      "dateUpdated": "2020-02-17 18:23:07.420",
      "config": {
        "editorSetting": {
          "language": "sql",
          "editOnDblClick": false,
          "completionKey": "TAB",
          "completionSupport": true
        },
        "colWidth": 12.0,
        "editorMode": "ace/mode/sql",
        "fontSize": 9.0,
        "results": {
          "0": {
            "graph": {
              "mode": "table",
              "height": 300.0,
              "optionOpen": false,
              "setting": {
                "table": {
                  "tableGridState": {},
                  "tableColumnTypeState": {
                    "names": {
                      "genreName": "string",
                      "totalTagged": "string"
                    },
                    "updated": false
                  },
                  "tableOptionSpecHash": "[{\"name\":\"useFilter\",\"valueType\":\"boolean\",\"defaultValue\":false,\"widget\":\"checkbox\",\"description\":\"Enable filter for columns\"},{\"name\":\"showPagination\",\"valueType\":\"boolean\",\"defaultValue\":false,\"widget\":\"checkbox\",\"description\":\"Enable pagination for better navigation\"},{\"name\":\"showAggregationFooter\",\"valueType\":\"boolean\",\"defaultValue\":false,\"widget\":\"checkbox\",\"description\":\"Enable a footer for displaying aggregated values\"}]",
                  "tableOptionValue": {
                    "useFilter": false,
                    "showPagination": false,
                    "showAggregationFooter": false
                  },
                  "updated": false,
                  "initialized": false
                }
              },
              "commonSetting": {}
            }
          }
        },
        "enabled": true
      },
      "settings": {
        "params": {},
        "forms": {}
      },
      "results": {
        "code": "SUCCESS",
        "msg": [
          {
            "type": "TABLE",
            "data": "genreName\ttotalTagged\nto-read\t112671045\ncurrently-reading\t7202432\nclassics\t2859522\nfiction\t2189310\nfavorites\t2037297\nfantasy\t813174\nowned\t576549\nbooks-i-own\t498089\nclassic\t467436\nhistorical-fiction\t353196\nnon-fiction\t318291\nliterature\t278822\nscience-fiction\t227997\nromance\t217684\nfavourites\t189857\nnovels\t184400\nsci-fi\t181296\nmystery\t172831\nplays\t172464\nowned-books\t165913\nhorror\t147097\nbook-club\t139078\nhistory\t138742\ndefault\t135697\nschool\t131043\nnonfiction\t130496\nkindle\t130046\nlibrary\t123726\nyoung-adult\t121427\nhistorical\t115312\nto-buy\t107780\nadult\t105885\naudiobook\t105304\ndrama\t99363\nmy-library\t95470\nphilosophy\t94624\nnovel\t92836\naudiobooks\t90415\n1001-books\t88850\nthriller\t88000\nmy-books\t86529\nadventure\t84631\npoetry\t82770\nseries\t77519\nadult-fiction\t75250\nmanga\t74428\nclassic-literature\t74217\nebook\t71610\nstephen-king\t69943\ncontemporary\t68594\nre-read\t65816\nliterary-fiction\t65428\nscience\t64594\nenglish\t63718\ndystopia\t62954\nhumor\t62896\naudio\t59676\nchildrens\t59368\ni-own\t59054\nshakespeare\t58622\nabandoned\t56860\nall-time-favorites\t56476\nread-for-school\t55283\n1001\t54446\ndystopian\t53409\ngeneral-fiction\t49566\namerican\t49316\nbritish\t49218\nclassics-to-read\t48546\nmemoir\t47622\nebooks\t47171\nshort-stories\t46602\nbiography\t46234\ncrime\t44615\nsci-fi-fantasy\t43571\nchick-lit\t43112\nhigh-school\t43085\nchildren\t41267\n20th-century\t41178\nya\t41168\n19th-century\t40996\nbooks\t40679\nfavorite-books\t40628\nown-it\t40530\nrory-gilmore-reading-challenge\t39549\nfor-school\t39079\nmagical-realism\t36938\nfavorite\t35834\ndnf\t35770\naudible\t34822\ntravel\t34657\nschool-books\t34576\nwish-list\t33627\ndid-not-finish\t33609\namerican-literature\t33547\n1001-books-to-read-before-you-die\t32873\nscifi\t31263\nclassic-fiction\t30598\nrussian\t30577\nliterary\t30333\n"
          },
          {
            "type": "TEXT",
            "data": ""
          }
        ]
      },
      "apps": [],
      "jobName": "paragraph_1581963787420_367638589",
      "id": "20191030-021752_1859690451",
      "dateCreated": "2020-02-17 18:23:07.420",
      "status": "READY",
      "errorMessage": "",
      "progressUpdateIntervalMs": 500
    },
    {
      "title": "Top100 fantasy books in publisher cluster 2",
      "text": "%sql\nselect title, publisher, publicationYear, averageRating, ratingsCount\nfrom genre_book_publisher_rank\nwhere prediction \u003d 2 and genreName \u003d \"fantasy\"\norder by ratingsCount desc\nlimit 100",
      "user": "anonymous",
      "dateUpdated": "2020-02-17 18:23:07.421",
      "config": {
        "editorSetting": {
          "language": "sql",
          "editOnDblClick": false,
          "completionKey": "TAB",
          "completionSupport": true
        },
        "colWidth": 12.0,
        "editorMode": "ace/mode/sql",
        "fontSize": 9.0,
        "title": true,
        "results": {
          "0": {
            "graph": {
              "mode": "table",
              "height": 300.0,
              "optionOpen": false,
              "setting": {
                "table": {
                  "tableGridState": {},
                  "tableColumnTypeState": {
                    "names": {
                      "title": "string",
                      "publisher": "string",
                      "publicationYear": "string",
                      "averageRating": "string",
                      "ratingsCount": "string"
                    },
                    "updated": false
                  },
                  "tableOptionSpecHash": "[{\"name\":\"useFilter\",\"valueType\":\"boolean\",\"defaultValue\":false,\"widget\":\"checkbox\",\"description\":\"Enable filter for columns\"},{\"name\":\"showPagination\",\"valueType\":\"boolean\",\"defaultValue\":false,\"widget\":\"checkbox\",\"description\":\"Enable pagination for better navigation\"},{\"name\":\"showAggregationFooter\",\"valueType\":\"boolean\",\"defaultValue\":false,\"widget\":\"checkbox\",\"description\":\"Enable a footer for displaying aggregated values\"}]",
                  "tableOptionValue": {
                    "useFilter": false,
                    "showPagination": false,
                    "showAggregationFooter": false
                  },
                  "updated": false,
                  "initialized": false
                }
              },
              "commonSetting": {}
            }
          }
        },
        "enabled": true
      },
      "settings": {
        "params": {},
        "forms": {}
      },
      "results": {
        "code": "SUCCESS",
        "msg": [
          {
            "type": "TABLE",
            "data": "title\tpublisher\tpublicationYear\taverageRating\tratingsCount\nThe Hobbit or There and Back Again\tHoughton Mifflin\t2002\t4.27\t2428508\nAngels \u0026 Demons (Robert Langdon, #1)\tPocket Books\t2006\t3.89\t2337887\nAnimal Farm\tNAL\t2003\t3.92\t2107966\nThe Fellowship of the Ring (The Lord of the Rings, #1)\tHoughton Mifflin Harcourt\t2003\t4.36\t2061150\nA Game of Thrones (A Song of Ice and Fire, #1)\tBantam\t2005\t4.45\t1652620\nThe Alchemist\tHarperCollins\t1993\t3.86\t1626274\nThe Da Vinci Code (Robert Langdon, #2)\tAnchor\t2006\t3.83\t1622463\nSlaughterhouse-Five\tDial Press\t1999\t4.07\t975421\nThe Odyssey\tPenguin Classics\t2006\t3.75\t743822\nOutlander (Outlander, #1)\tDell Publishing Company\t2005\t4.22\t649371\nA Clash of Kings  (A Song of Ice and Fire, #2)\tBantam\t2002\t4.41\t619448\nA Clash of Kings  (A Song of Ice and Fire, #2)\tBantam\t2002\t4.41\t619448\nHamlet\tCambridge University Press\t2005\t4.01\t591128\nThe Road\tAlfred A. Knopf\t2006\t3.96\t590066\nMacbeth\tSimon  Schuster\t2013\t3.89\t574525\nThe Two Towers (The Lord of the Rings, #2)\tHoughton Mifflin\t0\t4.44\t570453\nOne Hundred Years of Solitude\tHarper\t2003\t4.06\t561658\nCharlie and the Chocolate Factory (Charlie Bucket, #1)\tPuffin Books\t2005\t4.13\t537460\nDeception Point\tPocket Books\t2002\t3.7\t521580\nA Feast for Crows (A Song of Ice and Fire, #4)\tBantam Books\t2011\t4.13\t504428\nThe Chronicles of Narnia (Chronicles of Narnia, #1-7)\tHarperCollins\t2002\t4.26\t435772\nMisery\tNew English Library\t1988\t4.15\t413126\nThe Very Hungry Caterpillar\tPuffin Books\t1994\t4.29\t348639\nNeverwhere (London Below, #1)\tWilliam Morrow Paperbacks\t2003\t4.17\t334432\nThe Time Machine\tSignet Classics\t2002\t3.89\t331300\nThe Shadow of the Wind (The Cemetery of Forgotten Books, #1)\tPenguin Books\t2005\t4.26\t318388\nAtlas Shrugged\tPlume\t1999\t3.69\t317628\nLove in the Time of Cholera\tVintage International\t2003\t3.91\t316984\nThe BFG\tPuffin Books\t2001\t4.22\t299896\nThe Iliad\tPenguin Classics\t1999\t3.85\t280576\nLike Water for Chocolate\tBlack Swan\t1993\t3.95\t280447\n\u0027Salem\u0027s Lot\tNew English Library\t1991\t4.01\t275146\nBeloved\tVintage\t2004\t3.82\t272069\nPet Sematary\tPocket Books\t2005\t3.97\t257193\nThe Lorax\tRandom House Books for Young Readers\t1998\t4.35\t251955\nStranger in a Strange Land\tAce\t1991\t3.92\t247096\nThe Ultimate Hitchhiker\u0027s Guide to the Galaxy (Hitchhiker\u0027s Guide to the Galaxy, #1-5)\tDel Rey Books\t2002\t4.38\t245089\nA Little Princess\tPenguin Books\t2002\t4.2\t234999\nOdd Thomas (Odd Thomas, #1)\tBantam\t2006\t3.96\t224657\nPerfume: The Story of a Murderer\tPenguin Books\t1987\t4.02\t220428\nKafka on the Shore\tVintage International\t2006\t4.13\t216157\nDragonfly in Amber (Outlander, #2)\tBantam\t2001\t4.32\t216023\nBlack Beauty\tScholastic Paperbacks\t2003\t3.95\t203926\nRobinson Crusoe\tModern Library\t2001\t3.67\t203311\nThe Andromeda Strain (Andromeda, #1)\tAvon Books\t2003\t3.89\t197155\nVoyager (Outlander, #3)\tDelta\t2001\t4.39\t193839\nThe War of the Worlds\tModern Library\t2002\t3.82\t189834\nGulliver\u0027s Travels\tPenguin\t2003\t3.56\t189538\nSnow Crash\tBantam Books\t2000\t4.03\t187917\nSpeaker for the Dead (Ender\u0027s Saga, #2)\tTor Books\t1994\t4.06\t186410\nThe Angel Experiment (Maximum Ride, #1)\tGrand Central Publishing\t2006\t4.08\t185918\nThe Clan of the Cave Bear (Earth\u0027s Children, #1)\tBantam\t2002\t4.04\t184029\nDeath Note, Vol. 1: Boredom (Death Note, #1)\tVIZ Media LLC\t2005\t4.43\t169005\nThe Drawing of the Three (The Dark Tower, #2)\tSignet\t2003\t4.23\t168854\nThe Canterbury Tales\tPenguin Classics\t2003\t3.49\t163940\nThe Amazing Adventures of Kavalier \u0026 Clay\tPicador USA\t2001\t4.17\t163581\nLife, the Universe and Everything (Hitchhiker\u0027s Guide to the Galaxy, #3)\tDel Rey\t2005\t4.2\t162798\nThe Silmarillion (Middle-Earth Universe)\tHoughton Mifflin Harcourt\t2004\t3.92\t161058\nThe Wind-Up Bird Chronicle\tKnopf\t1997\t4.17\t160901\nDon Quixote\tPenguin Classics\t2003\t3.87\t155256\nJonathan Strange \u0026 Mr Norrell\tTor Books\t2006\t3.82\t155117\nBag of Bones\tPocket Books\t1999\t3.89\t151845\nThinner\tSignet\t1996\t3.71\t150945\nThe Wind in the Willows\tPenguin Books\t2005\t3.99\t144729\nCongo\tAvon Books\t2003\t3.58\t142611\nAnimal Farm / 1984\tHoughton Mifflin Harcourt\t2003\t4.28\t142162\nDrums of Autumn (Outlander, #4)\tDelta\t2001\t4.35\t141387\nBleach, Volume 01\tVIZ Media LLC\t2004\t4.22\t138705\nWizard and Glass (The Dark Tower, #4)\tNew English Library\t2003\t4.25\t126759\nBrave New World / Brave New World Revisited\tHarper Perennial Modern Classics\t2005\t4.16\t125594\nThe Fiery Cross (Outlander, #5)\tDell\t2005\t4.27\t124923\nWolves of the Calla (The Dark Tower, #5)\tPocket Books\t2006\t4.18\t124418\nNight Shift\tNew English Library\t1979\t3.99\t122916\nXenocide (Ender\u0027s Saga, #3)\tTor Books\t1996\t3.79\t117916\nThe Screwtape Letters\tHarperCollins\t2001\t4.22\t116821\nFor One More Day\tHachette Books\t2006\t4.1\t111831\nAnthem\tNAL\t1999\t3.63\t108856\nFullmetal Alchemist, Vol. 1 (Fullmetal Alchemist, #1)\tVIZ Media LLC\t2005\t4.5\t107845\nThe Dark Half\tNew English Library\t1990\t3.77\t107597\nBlindness\tMariner Books\t1999\t4.11\t107047\nA Crown of Swords (Wheel of Time, #7)\tTor Books\t1997\t4.03\t103871\nA Breath of Snow and Ashes (Outlander, #6)\tDelta\t2006\t4.44\t103375\nJ.R.R. Tolkien 4-Book Boxed Set: The Hobbit and The Lord of the Rings\tBallantine Books\t2012\t4.59\t99261\nSkeleton Crew\tWarner Books\t1993\t3.95\t95128\nSo Long, and Thanks for All the Fish (Hitchhiker\u0027s Guide to the Galaxy, #4)\tPicador USA\t2002\t4.09\t93968\nThe Long Walk\tSignet\t1999\t4.11\t89386\nHorton Hears a Who!\tRandom House Books for Young Readers\t1990\t4.17\t87885\nMidnight\u0027s Children\tVintage\t1995\t3.98\t85801\nThe Aeneid\tVintage\t1990\t3.83\t85589\nThe Divine Comedy\tEveryman\u0027s Library\t1995\t4.07\t84137\n\u0027Salem\u0027s Lot\tDoubleday\t2005\t4.25\t82255\nThe Running Man\tSignet\t1999\t3.86\t82198\nCryptonomicon\tAvon\t2002\t4.25\t81783\nThe Celestine Prophecy (Celestine Prophecy, #1)\tWarner Books\t1995\t3.64\t81125\nThe Farthest Shore (Earthsea Cycle, #3)\tGallery Books\t2004\t4.13\t78537\nSputnik Sweetheart\tVintage\t2002\t3.82\t76038\nHearts in Atlantis\tNew English Library\t2001\t3.82\t72174\nEverything\u0027s Eventual: 14 Dark Tales\tPocket Books\t2005\t3.96\t71521\nBy the River Piedra I Sat Down and Wept\tHarperOne\t2006\t3.57\t69696\nThe Mermaid Chair\tPenguin Books\t2006\t3.13\t67646\n"
          },
          {
            "type": "TEXT",
            "data": ""
          }
        ]
      },
      "apps": [],
      "jobName": "paragraph_1581963787420_-1708003400",
      "id": "20191030-021906_744045201",
      "dateCreated": "2020-02-17 18:23:07.421",
      "status": "READY",
      "errorMessage": "",
      "progressUpdateIntervalMs": 500
    },
    {
      "text": "%spark\ngenreToBookWithPublisherAndRankTable.write.mode(\"overwrite\").parquet(\"/odsc/genres_books_publishers_ranked.parquet\")",
      "user": "anonymous",
      "dateUpdated": "2020-02-17 18:23:07.421",
      "config": {
        "editorSetting": {
          "language": "scala",
          "editOnDblClick": false,
          "completionKey": "TAB",
          "completionSupport": true
        },
        "colWidth": 12.0,
        "editorMode": "ace/mode/scala",
        "fontSize": 9.0,
        "results": {},
        "enabled": true
      },
      "settings": {
        "params": {},
        "forms": {}
      },
      "results": {
        "code": "SUCCESS",
        "msg": []
      },
      "apps": [],
      "jobName": "paragraph_1581963787421_-594266458",
      "id": "20191030-041331_426148616",
      "dateCreated": "2020-02-17 18:23:07.421",
      "status": "READY",
      "errorMessage": "",
      "progressUpdateIntervalMs": 500
    },
    {
      "text": "%md\n### And now the real Conclusion\n1. We are going to recommend the next 10 books for any book liked\n\nEpic Conclusion: http://localhost:8080/#/notebook/2ERUV16BU",
      "user": "anonymous",
      "dateUpdated": "2020-02-17 18:23:07.421",
      "config": {
        "tableHide": false,
        "editorSetting": {
          "language": "markdown",
          "editOnDblClick": true,
          "completionKey": "TAB",
          "completionSupport": false
        },
        "colWidth": 12.0,
        "editorMode": "ace/mode/markdown",
        "fontSize": 9.0,
        "editorHide": true,
        "results": {},
        "enabled": true
      },
      "settings": {
        "params": {},
        "forms": {}
      },
      "results": {
        "code": "SUCCESS",
        "msg": [
          {
            "type": "HTML",
            "data": "\u003cdiv class\u003d\"markdown-body\"\u003e\n\u003ch3\u003eAnd now the real Conclusion\u003c/h3\u003e\n\u003col\u003e\n  \u003cli\u003eWe are going to recommend the next 10 books for any book liked\u003c/li\u003e\n\u003c/ol\u003e\n\u003cp\u003eEpic Conclusion: \u003ca href\u003d\"http://localhost:8080/#/notebook/2ERUV16BU\"\u003ehttp://localhost:8080/#/notebook/2ERUV16BU\u003c/a\u003e\u003c/p\u003e\n\u003c/div\u003e"
          }
        ]
      },
      "apps": [],
      "jobName": "paragraph_1581963787421_1931350769",
      "id": "20191030-040919_551568009",
      "dateCreated": "2020-02-17 18:23:07.421",
      "status": "READY",
      "errorMessage": "",
      "progressUpdateIntervalMs": 500
    }
  ],
  "name": "ODSC/6-SparkML-Conclusion",
  "id": "2F1RZ6CWX",
  "noteParams": {},
  "noteForms": {},
  "angularObjects": {
    "md:shared_process": [],
    "spark:shared_process": []
  },
  "config": {
    "isZeppelinNotebookCronEnable": false
  },
  "info": {}
}